LECPython/LECPythonLib.deps.json
LECPython/LECPythonLib.dll
LECPython/LECPythonLib.pdb
LECPython/LECPythonLib.py
LECPython/Microsoft.Win32.SystemEvents.dll
LECPython/Newtonsoft.Json.dll
LECPython/System.Collections.Immutable.dll
LECPython/System.Data.SqlClient.dll
LECPython/System.Drawing.Common.dll
LECPython/System.Formats.Nrbf.dll
LECPython/System.IO.Ports.dll
LECPython/System.Reflection.Metadata.dll
LECPython/System.Resources.Extensions.dll
LECPython/__init__.py
LECPython/libSystem.IO.Ports.Native.so
LECPython-1.2.3.6.dist-info/METADATA
LECPython-1.2.3.6.dist-info/WHEEL
LECPython-1.2.3.6.dist-info/top_level.txt
LECPython-1.2.3.6.dist-info/RECORD
