Metadata-Version: 2.1
Name: LECPython
Version: 1.2.3.6
Summary: LECPython is a Python component developed in C# that enables seamless communication between Python and PLCs...
Home-page: https://github.com/xeden3/LECPython
Author: xeden3
Author-email: james@sctmes.com
Project-URL: Documentation, http://lecpserver.com:3003/
Project-URL: Source, https://github.com/xeden3/LECPython
Project-URL: Bug Tracker, https://github.com/xeden3/LECPython/issues
Classifier: Programming Language :: Python :: 3
Classifier: License :: OSI Approved :: MIT License
Requires-Dist: pythonnet (==3.0.4)
